app/__init__.py
app/cli.py
app/__pycache__/__init__.cpython-39.pyc
app/__pycache__/cli.cpython-39.pyc
app/core/__init__.py
app/core/trainer.py
app/core/__pycache__/__init__.cpython-39.pyc
app/core/__pycache__/trainer.cpython-39.pyc
bert_trainer-1.0.2.dev8.dist-info/METADATA
bert_trainer-1.0.2.dev8.dist-info/WHEEL
bert_trainer-1.0.2.dev8.dist-info/entry_points.txt
bert_trainer-1.0.2.dev8.dist-info/top_level.txt
bert_trainer-1.0.2.dev8.dist-info/RECORD
