Metadata-Version: 2.4
Name: bert-trainer
Version: 1.0.2.dev8
Summary: A dataset container for al-1s project.
Author-email: stupidfish001 <shovel@hscsec.cn>
Classifier: Programming Language :: Python :: 3
Classifier: License :: OSI Approved :: MIT License
Classifier: Operating System :: OS Independent
Requires-Python: >=3.6
Requires-Dist: typer==0.15.3
Requires-Dist: click==8.1.8
Requires-Dist: loguru
Requires-Dist: pandas
Requires-Dist: torch
Requires-Dist: numpy
Requires-Dist: transformers
Requires-Dist: tqdm
Requires-Dist: scikit-learn
Requires-Dist: fastparquet
Requires-Dist: accelerate>=0.26.0
